duohub/__init__.py
duohub/client.py
duohub/environment.py
duohub/exceptions.py
duohub/methods/files/create.py
duohub/methods/files/upload.py
duohub/methods/memory/add_files.py
duohub/methods/memory/create.py
duohub/methods/memory/delete_file.py
duohub/methods/memory/start_ingestion.py
duohub/methods/messages/create.py
duohub/methods/messages/delete.py
duohub/methods/messages/get.py
duohub/methods/messages/list.py
duohub/methods/sessions/create.py
duohub/methods/sessions/delete.py
duohub/methods/sessions/get.py
duohub/methods/sessions/list.py
duohub/methods/users/create.py
duohub/methods/users/delete.py
duohub/methods/users/get.py
duohub/methods/users/list.py
duohub/models/enums.py
duohub/utils.py
duohub-2.2.0.dist-info/LICENSE
duohub-2.2.0.dist-info/METADATA
duohub-2.2.0.dist-info/WHEEL
duohub-2.2.0.dist-info/RECORD
