Metadata-Version: 2.1
Name: duohub
Version: 2.2.0
Summary: duohub retriever package for querying memories
Home-page: https://github.com/duohub-ai/duohub-py
License: ISC
Keywords: duohub,graphrag,voiceai,rag,retrieval,chatbot
Author: Oseh Mathias
Author-email: o@matmail.me
Requires-Python: >=3.9,<4.0
Classifier: Development Status :: 3 - Alpha
Classifier: Intended Audience :: Developers
Classifier: License :: OSI Approved
Classifier: License :: OSI Approved :: ISC License (ISCL)
Classifier: Programming Language :: Python :: 3
Classifier: Programming Language :: Python :: 3.9
Classifier: Programming Language :: Python :: 3.10
Classifier: Programming Language :: Python :: 3.11
Classifier: Programming Language :: Python :: 3.12
Classifier: Programming Language :: Python :: 3.13
Requires-Dist: httpx (>=0.27.2,<0.28.0)
Requires-Dist: tqdm (>=4.67.1,<5.0.0)
Project-URL: Bug Tracker, https://github.com/duohub-ai/duohub-py/issues
Project-URL: Documentation, https://github.com/duohub-ai/duohub-py#readme
Project-URL: Repository, https://github.com/duohub-ai/duohub-py
